mechDraw/Shapes.py
mechDraw/Structures.py
mechDraw/Styles.py
mechDraw/__init__.py
mechDraw/ex.py
mechDraw/shapes_ex.py
mechDraw/tests_tests.py
mechDraw-0.1.dist-info/WHEEL
mechDraw-0.1.dist-info/METADATA
mechDraw-0.1.dist-info/RECORD
