Metadata-Version: 2.1
Name: mechDraw
Version: 0.1
Summary: This is a python drawing module.
Home-page: https://github.com/BrianChevalier/mechDraw
License: UNKNOWN
Author: Brian Chevalier
Author-email: BrianChevalier@gmail.com
